setup.cfg
setup.py
statipy317_distributions/Binomialdistribution.py
statipy317_distributions/Gaussiandistribution.py
statipy317_distributions/Generaldistribution.py
statipy317_distributions/__init__.py
statipy317_distributions.egg-info/PKG-INFO
statipy317_distributions.egg-info/SOURCES.txt
statipy317_distributions.egg-info/dependency_links.txt
statipy317_distributions.egg-info/not-zip-safe
statipy317_distributions.egg-info/top_level.txt